sanakirja/__init__.py
sanakirja/api.py
sanakirja/cli.py
sanakirja/tag_parser.py
sanakirja_org-1.1.2.dist-info/licenses/LICENSE
sanakirja_org-1.1.2.dist-info/METADATA
sanakirja_org-1.1.2.dist-info/WHEEL
sanakirja_org-1.1.2.dist-info/entry_points.txt
sanakirja_org-1.1.2.dist-info/top_level.txt
sanakirja_org-1.1.2.dist-info/RECORD
