Metadata-Version: 2.4
Name: sanakirja-org
Version: 1.1.2
Summary: An unofficial Python API and CLI tool for sanakirja.org.
Author: AceHanded
Project-URL: Source Code, https://github.com/AceHanded/sanakirja-org
Project-URL: Bug Reports, https://github.com/AceHanded/sanakirja-org/issues
Keywords: sanakirja,translation,CLI,API
Classifier: Environment :: Console
Classifier: Intended Audience :: Education
Classifier: Intended Audience :: Developers
Classifier: Natural Language :: English
Classifier: Natural Language :: Finnish
Classifier: Operating System :: OS Independent
Classifier: Programming Language :: Python
Classifier: Programming Language :: Python :: 3.8
Classifier: Programming Language :: Python :: 3.9
Classifier: Programming Language :: Python :: 3.10
Classifier: Programming Language :: Python :: 3.11
Classifier: Programming Language :: Python :: 3.12
Classifier: Programming Language :: Python :: 3.13
Classifier: Topic :: Internet
Classifier: Topic :: Internet :: WWW/HTTP
Classifier: Topic :: Utilities
Classifier: Topic :: Text Processing
Classifier: Topic :: Text Processing :: Linguistic
Requires-Python: >=3.8
License-File: LICENSE
Dynamic: license-file
